PyDSALib/AVL_tree.py
PyDSALib/__init__.py
PyDSALib/binary_tree.py
PyDSALib/binary_tree_algorithms.py
PyDSALib/deque.py
PyDSALib/graph.py
PyDSALib/graph_algorithms.py
PyDSALib/heap.py
PyDSALib/linked_list.py
PyDSALib/pretty_printer.py
PyDSALib/priority_queue.py
PyDSALib/queue.py
PyDSALib/stack.py
PyDSALib-0.2.dist-info/LICENSE
PyDSALib-0.2.dist-info/METADATA
PyDSALib-0.2.dist-info/WHEEL
PyDSALib-0.2.dist-info/top_level.txt
PyDSALib-0.2.dist-info/RECORD
