Metadata-Version: 2.1
Name: PyDSALib
Version: 0.2
Summary: A library of data structures, implemented in Python for Python
Home-page: https://github.com/HerrHruby/PyDSALib
Author: Ian Wu
Author-email: ianyhwu.97@gmail.com
License: UNKNOWN
Platform: UNKNOWN
Classifier: Programming Language :: Python :: 3
Classifier: License :: OSI Approved :: MIT License
Classifier: Operating System :: OS Independent
Requires-Python: >=3.6
